openregister/__init__.py
openregister/_base_client.py
openregister/_client.py
openregister/_compat.py
openregister/_constants.py
openregister/_exceptions.py
openregister/_files.py
openregister/_models.py
openregister/_qs.py
openregister/_resource.py
openregister/_response.py
openregister/_streaming.py
openregister/_types.py
openregister/_version.py
openregister/py.typed
openregister/_utils/__init__.py
openregister/_utils/_compat.py
openregister/_utils/_datetime_parse.py
openregister/_utils/_logs.py
openregister/_utils/_proxy.py
openregister/_utils/_reflection.py
openregister/_utils/_resources_proxy.py
openregister/_utils/_streams.py
openregister/_utils/_sync.py
openregister/_utils/_transform.py
openregister/_utils/_typing.py
openregister/_utils/_utils.py
openregister/lib/.keep
openregister/resources/__init__.py
openregister/resources/company.py
openregister/resources/document.py
openregister/resources/person.py
openregister/resources/search.py
openregister/types/__init__.py
openregister/types/company_address.py
openregister/types/company_capital.py
openregister/types/company_get_contact_v0_response.py
openregister/types/company_get_details_v1_params.py
openregister/types/company_get_details_v1_response.py
openregister/types/company_get_financials_v1_response.py
openregister/types/company_get_holdings_v1_response.py
openregister/types/company_get_owners_v1_params.py
openregister/types/company_get_owners_v1_response.py
openregister/types/company_legal_form.py
openregister/types/company_name.py
openregister/types/company_purpose.py
openregister/types/company_register.py
openregister/types/company_register_type.py
openregister/types/company_relation_type.py
openregister/types/company_search.py
openregister/types/document_get_cached_v1_response.py
openregister/types/document_get_realtime_v1_params.py
openregister/types/document_get_realtime_v1_response.py
openregister/types/entity_type.py
openregister/types/merged_report_row.py
openregister/types/merged_report_table.py
openregister_sdk-2.1.0.dist-info/METADATA
openregister_sdk-2.1.0.dist-info/WHEEL
openregister_sdk-2.1.0.dist-info/licenses/LICENSE
openregister_sdk-2.1.0.dist-info/RECORD
